cochl_sense_api/__init__.py
cochl_sense_api/api_client.py
cochl_sense_api/api_response.py
cochl_sense_api/configuration.py
cochl_sense_api/exceptions.py
cochl_sense_api/py.typed
cochl_sense_api/rest.py
cochl_sense_api/api/__init__.py
cochl_sense_api/api/audio_session_api.py
cochl_sense_api/models/__init__.py
cochl_sense_api/models/audio_chunk.py
cochl_sense_api/models/create_session.py
cochl_sense_api/models/created_session.py
cochl_sense_api/models/generic_error.py
cochl_sense_api/models/page.py
cochl_sense_api/models/predict_request.py
cochl_sense_api/models/predict_response.py
cochl_sense_api/models/sense.py
cochl_sense_api/models/sense_event.py
cochl_sense_api/models/sense_event_tag.py
cochl_sense_api/models/session_refs.py
cochl_sense_api/models/session_result.py
cochl_sense_api/models/session_status.py
cochl_sense_api/models/session_type.py
cochl_sense_api/models/update_session.py
cochl_sense_api-1.7.11.dist-info/METADATA
cochl_sense_api-1.7.11.dist-info/WHEEL
cochl_sense_api-1.7.11.dist-info/licenses/LICENSE
cochl_sense_api-1.7.11.dist-info/RECORD
