Metadata-Version: 2.4
Name: cochl-sense-api
Version: 1.7.11
Summary: Cochl Sense API
Project-URL: Homepage, https://github.com/cochlearai/sense-api-samples
Project-URL: Issues, https://github.com/cochlearai/sense-api-samples/issues
Author-email: Cochl <support@cochl.ai>
License-File: LICENSE
Classifier: License :: OSI Approved :: MIT License
Classifier: Operating System :: OS Independent
Classifier: Programming Language :: Python :: 3
Requires-Python: >=3.9
Requires-Dist: pydantic>=2.11.4
Requires-Dist: python-dateutil>=2.9.0.post0
Requires-Dist: urllib3>=2.4.0
